notevault-2.0.0.dist-info/METADATA
notevault-2.0.0.dist-info/WHEEL
notevault-2.0.0.dist-info/entry_points.txt
notevault/__init__.py
notevault/create_schemas.py
notevault/edit_content.py
notevault/entrypoints/cli.py
notevault/entrypoints/main.py
notevault/entrypoints/main_many.py
notevault/environment.py
notevault/helper.py
notevault/model/__init__.py
notevault/model/create_models.py
notevault/model/orm.py
notevault/parse/__init__.py
notevault/parse/do_parse.py
notevault/parse/helper.py
notevault/parse/markdown_parser.py
notevault/parse/props_parser.py
notevault/parse/section.py
notevault/validate_schema.py
notevault-2.0.0.dist-info/RECORD
