Metadata-Version: 2.1
Name: notevault
Version: 2.0.0
Summary: save parsed markdown into sqlite db
Author-Email: sysid <sysid@gmx.de>
License: MIT
Requires-Python: >=3.10
Requires-Dist: sqlite-utils>=3.35.1
Requires-Dist: markdown>=3.5.1
Requires-Dist: bs4>=0.0.1
Requires-Dist: pydantic>=2.4.2
Requires-Dist: dateparser>=1.1.8
Requires-Dist: sqlalchemy>=2.0.23
Requires-Dist: alembic>=1.12.1
Requires-Dist: typer>=0.9.0
Requires-Dist: pydantic-settings>=2.0.3
Requires-Dist: pyyaml>=6.0.1
Requires-Dist: parsy>=2.1
